vsmodupdater/__init__.py
vsmodupdater/api.py
vsmodupdater/cli.py
vsmodupdater/fs.py
vsmodupdater/py.typed
vsmodupdater/util.py
vsmodupdater/version.py
vsmodupdater-0.6.3.dist-info/LICENSE
vsmodupdater-0.6.3.dist-info/METADATA
vsmodupdater-0.6.3.dist-info/WHEEL
vsmodupdater-0.6.3.dist-info/entry_points.txt
vsmodupdater-0.6.3.dist-info/top_level.txt
vsmodupdater-0.6.3.dist-info/RECORD
