Metadata-Version: 2.1
Name: vsmodupdater
Version: 0.6.3
Summary: a mod updater for VintageStory
Author-email: Ferdinand B <me+vsmodupdater@yrlf.at>
Project-URL: Homepage, https://github.com/Ferdi265/vsmodupdater
Project-URL: Bug Tracker, https://github.com/Ferdi265/vsmodupdater/issues
Classifier: Programming Language :: Python :: 3
Classifier: License :: OSI Approved :: GNU General Public License v3 (GPLv3)
Classifier: Operating System :: OS Independent
Requires-Python: >=3.7
License-File: LICENSE
Requires-Dist: requests ~=2.28
